{"tileset_filename": "castle.json", "width": 20, "height": 20, "cell_size": 20, "tiles": [[0, 0, 0, 0, 0, 0, 0, 0, 0, 0, 0, 0, 0, 0, 0, 0, 0, 0, 0, 0], [0, 0, 0, 0, 0, 0, 0, 0, 0, 0, 0, 0, 0, 0, 0, 0, 0, 0, 0, 0], [0, 0, 0, 0, 0, 0, 0, 0, 0, 0, 0, 0, 0, 0, 0, 0, 0, 0, 0, 0], [0, 0, 0, 0, 0, 0, 0, 0, 0, 0, 0, 0, 0, 0, 0, 0, 0, 0, 0, 0], [0, 0, 0, 0, 139, 139, 139, 139, 139, 139, 139, 139, 139, 139, 139, 139, 0, 0, 0, 0], [0, 0, 0, 0, 139, 1, 2, 36, 2, 2, 2, 2, 36, 2, 3, 139, 0, 0, 0, 0], [0, 0, 0, 0, 139, 17, 145, 145, 145, 145, 145, 145, 145, 145, 19, 139, 0, 0, 0, 0], [0, 0, 0, 0, 139, 17, 145, 84, 145, 145, 136, 145, 145, 145, 19, 139, 0, 0, 0, 0], [0, 0, 0, 0, 139, 17, 145, 100, 145, 145, 145, 145, 102, 145, 19, 139, 0, 0, 0, 0], [0, 0, 0, 0, 139, 17, 145, 145, 145, 145, 145, 145, 145, 145, 19, 139, 0, 0, 0, 0], [0, 0, 0, 0, 139, 17, 145, 84, 145, 145, 145, 145, 84, 145, 19, 139, 0, 0, 0, 0], [0, 0, 0, 0, 139, 17, 110, 100, 145, 145, 145, 145, 100, 145, 19, 139, 0, 0, 0, 0], [0, 0, 0, 0, 139, 17, 145, 145, 145, 153, 145, 145, 145, 145, 19, 139, 0, 0, 0, 0], [0, 0, 0, 0, 139, 17, 145, 145, 145, 145, 145, 145, 110, 145, 19, 139, 0, 0, 0, 0], [0, 0, 0, 0, 139, 17, 2, 133, 2, 2, 2, 2, 2, 2, 19, 139, 0, 0, 0, 0], [0, 0, 0, 0, 139, 139, 139, 0, 139, 139, 139, 139, 139, 139, 139, 139, 0, 0, 0, 0], [0, 0, 0, 0, 0, 0, 0, 0, 0, 0, 0, 0, 0, 0, 0, 0, 0, 0, 0, 0], [0, 0, 0, 0, 0, 0, 0, 0, 0, 0, 0, 0, 0, 0, 0, 0, 0, 0, 0, 0], [0, 0, 0, 0, 0, 0, 0, 0, 0, 0, 0, 0, 0, 0, 0, 0, 0, 0, 0, 0], [0, 0, 0, 0, 0, 0, 0, 0, 0, 0, 0, 0, 0, 0, 0, 0, 0, 0, 0, 0]], "passable_layer": [[true, true, true, true, true, true, true, true, true, true, true, true, true, true, true, true, true, true, true, true], [true, true, true, true, true, true, true, true, true, true, true, true, true, true, true, true, true, true, true, true], [true, true, true, true, true, true, true, true, true, true, true, true, true, true, true, true, true, true, true, true], [true, true, true, true, true, true, true, true, true, true, true, true, true, true, true, true, true, true, true, true], [true, true, true, true, false, false, false, false, false, false, false, false, false, false, false, false, true, true, true, true], [true, true, true, true, false, false, false, false, false, false, false, false, false, false, false, false, true, true, true, true], [true, true, true, true, false, false, true, true, true, true, true, true, true, true, false, false, true, true, true, true], [true, true, false, false, false, false, true, true, true, true, true, true, true, true, false, false, true, true, true, true], [true, true, false, true, false, false, true, true, true, true, true, true, false, true, false, false, true, true, true, true], [true, true, false, true, false, false, true, true, true, true, true, true, true, true, false, false, true, true, true, true], [true, true, false, true, false, false, true, true, true, true, true, true, false, true, false, false, true, true, true, true], [true, true, false, true, false, false, false, true, true, true, true, true, false, true, false, false, true, true, true, true], [true, true, false, true, false, false, true, true, true, true, true, true, true, true, false, false, true, true, true, true], [true, true, false, true, false, false, true, true, true, true, true, true, false, true, false, false, true, true, true, true], [true, true, false, true, false, false, false, true, false, false, false, false, false, false, false, false, true, true, true, true], [true, true, false, true, false, false, false, true, false, false, false, false, false, false, false, false, true, true, true, true], [true, true, false, true, false, true, true, true, false, true, true, true, true, true, true, true, true, true, true, true], [true, true, false, true, true, true, false, false, false, true, true, true, true, true, true, true, true, true, true, true], [true, true, false, false, false, false, false, true, true, true, true, true, true, true, true, true, true, true, true, true], [true, true, true, true, true, true, true, true, true, true, true, true, true, true, true, true, true, true, true, true]]}